{
  "cities": [
    {
      "cityName": "Lisbon",
      "country": "Portugal",
      "emoji": "🇵🇹",
      "date": "2027-10-31T15:59:59.138Z",
      "notes": "My favorite city so far!",
      "position": {
        "lat": 38.727881642324164,
        "lng": -9.140900099907554
      },
      "id": "73930385"
    },
    {
      "cityName": "Madrid",
      "country": "Spain",
      "emoji": "🇪🇸",
      "date": "2027-07-15T08:22:53.976Z",
      "notes": "",
      "position": {
        "lat": 40.46635901755316,
        "lng": -3.7133789062500004
      },
      "id": "17806751"
    },
    {
      "cityName": "Berlin",
      "country": "Germany",
      "emoji": "🇩🇪",
      "date": "2027-02-12T09:24:11.863Z",
      "notes": "Amazing 😃",
      "position": {
        "lat": 52.53586782505711,
        "lng": 13.376933665713324
      },
      "id": "98443197"
    },
    {
      "id": "a91c",
      "cityName": "Mong Cai",
      "country": "Viet Nam",
      "emoji": "🇻🇳",
      "date": "2024-02-28T17:06:15.648Z",
      "notes": "",
      "position": {
        "lat": "21.537096667920327",
        "lng": "107.9810530190284"
      }
    },
    {
      "id": "e5bb",
      "cityName": "Delhi",
      "country": "India",
      "emoji": "🇮🇳",
      "date": "2024-02-28T17:42:12.096Z",
      "notes": "",
      "position": {
        "lat": "28.576747222210614",
        "lng": "77.1283525439531"
      }
    },
    {
      "id": "cba8",
      "cityName": "Beijing",
      "country": "China",
      "emoji": "🇨🇳",
      "date": "2024-03-01T14:41:24.656Z",
      "notes": "",
      "position": {
        "lat": "39.80457867297352",
        "lng": "116.54296875000001"
      }
    }
  ]
}